Dym_Env/__init__.py
Dym_Env/envs/Dym_Env.py
Dym_Env/envs/__init__.py
Dym_Env-0.0.2.dist-info/METADATA
Dym_Env-0.0.2.dist-info/WHEEL
Dym_Env-0.0.2.dist-info/top_level.txt
Dym_Env-0.0.2.dist-info/RECORD
