Metadata-Version: 2.1
Name: Dym-Env
Version: 0.0.2
Summary: A OpenAI Gym Env for Dym
Home-page: UNKNOWN
License: UNKNOWN
Platform: UNKNOWN
Requires: gym
